keras_nlp/__init__.py
keras_nlp/layers/__init__.py
keras_nlp/metrics/__init__.py
keras_nlp/models/__init__.py
keras_nlp/samplers/__init__.py
keras_nlp/src/__init__.py
keras_nlp/src/api_export.py
keras_nlp/src/conftest.py
keras_nlp/src/backend/__init__.py
keras_nlp/src/backend/config.py
keras_nlp/src/backend/keras.py
keras_nlp/src/backend/ops.py
keras_nlp/src/backend/random.py
keras_nlp/src/layers/__init__.py
keras_nlp/src/layers/modeling/__init__.py
keras_nlp/src/layers/modeling/cached_multi_head_attention.py
keras_nlp/src/layers/modeling/cached_multi_head_attention_test.py
keras_nlp/src/layers/modeling/f_net_encoder.py
keras_nlp/src/layers/modeling/f_net_encoder_test.py
keras_nlp/src/layers/modeling/lora_dense.py
keras_nlp/src/layers/modeling/lora_dense_test.py
keras_nlp/src/layers/modeling/masked_lm_head.py
keras_nlp/src/layers/modeling/masked_lm_head_test.py
keras_nlp/src/layers/modeling/position_embedding.py
keras_nlp/src/layers/modeling/position_embedding_test.py
keras_nlp/src/layers/modeling/reversible_embedding.py
keras_nlp/src/layers/modeling/reversible_embedding_test.py
keras_nlp/src/layers/modeling/rotary_embedding.py
keras_nlp/src/layers/modeling/rotary_embedding_test.py
keras_nlp/src/layers/modeling/sine_position_encoding.py
keras_nlp/src/layers/modeling/sine_position_encoding_test.py
keras_nlp/src/layers/modeling/token_and_position_embedding.py
keras_nlp/src/layers/modeling/token_and_position_embedding_test.py
keras_nlp/src/layers/modeling/transformer_decoder.py
keras_nlp/src/layers/modeling/transformer_decoder_test.py
keras_nlp/src/layers/modeling/transformer_encoder.py
keras_nlp/src/layers/modeling/transformer_encoder_test.py
keras_nlp/src/layers/modeling/transformer_layer_utils.py
keras_nlp/src/layers/modeling/transformer_layer_utils_test.py
keras_nlp/src/layers/preprocessing/__init__.py
keras_nlp/src/layers/preprocessing/masked_lm_mask_generator.py
keras_nlp/src/layers/preprocessing/masked_lm_mask_generator_test.py
keras_nlp_nightly-0.0.0.dist-info/METADATA
keras_nlp_nightly-0.0.0.dist-info/WHEEL
keras_nlp_nightly-0.0.0.dist-info/top_level.txt
keras_nlp_nightly-0.0.0.dist-info/RECORD
